.gitignore
setup.py
ebs/__init__.py
ebs/linuxnode/__init__.py
ebs/linuxnode/gui/__init__.py
ebs/linuxnode/gui/kivy/__init__.py
ebs/linuxnode/gui/kivy/camera/__init__.py
ebs/linuxnode/gui/kivy/camera/mixin.py
ebs_linuxnode_gui_kivy_camera.egg-info/PKG-INFO
ebs_linuxnode_gui_kivy_camera.egg-info/SOURCES.txt
ebs_linuxnode_gui_kivy_camera.egg-info/dependency_links.txt
ebs_linuxnode_gui_kivy_camera.egg-info/requires.txt
ebs_linuxnode_gui_kivy_camera.egg-info/top_level.txt
example/app.py
example/node.py
example/run.py