Metadata-Version: 2.1
Name: ebs-linuxnode-gui-kivy-camera
Version: 1.1.1
Summary: Camera infrastructure for linuxnode applications
Home-page: https://github.com/ebs-universe/ebs-linuxnode-kivy-camera
Author: Chintalagiri Shashank
Author-email: shashank.chintalagiri@gmail.com
Classifier: Development Status :: 5 - Production/Stable
Classifier: Intended Audience :: Developers
Classifier: License :: OSI Approved :: GNU General Public License v3 or later (GPLv3+)
Classifier: Programming Language :: Python
Classifier: Programming Language :: Python :: 3
Classifier: Programming Language :: Python :: 3.6
Classifier: Operating System :: POSIX :: Linux
Requires-Dist: setuptools-scm
Requires-Dist: kivy_garden.ebs.camera>=1.2.0
Requires-Dist: ebs-linuxnode-camera>=1.1.0
Requires-Dist: ebs-linuxnode-gui-kivy-core>=2.0
